[{"0":[{"TEAM_ID":1610612760,"ABBREVIATION":"OKC","NICKNAME":"Thunder","YEARFOUNDED":1967,"CITY":"Oklahoma City","ARENA":"Paycom Center","ARENACAPACITY":null,"OWNER":"Clay Bennett","GENERALMANAGER":"Sam Presti","HEADCOACH":"Mark Daigneault","DLEAGUEAFFILIATION":"Oklahoma City Blue"}]},{"0":[{"TEAM_ID":1610612760,"CITY":"Oklahoma City","NICKNAME":"Thunder","YEARFOUNDED":2008,"YEARACTIVETILL":2019},{"TEAM_ID":1610612760,"CITY":"Seattle","NICKNAME":"SuperSonics","YEARFOUNDED":1967,"YEARACTIVETILL":2007}]},{"0":[{"ACCOUNTTYPE":"Facebook","WEBSITE_LINK":"https:\/\/www.facebook.com\/OKCThunder"},{"ACCOUNTTYPE":"Instagram","WEBSITE_LINK":"https:\/\/instagram.com\/okcthunder"},{"ACCOUNTTYPE":"Twitter","WEBSITE_LINK":"https:\/\/twitter.com\/okcthunder"}]},{"0":[{"YEARAWARDED":1979,"OPPOSITETEAM":"Washington Bullets"}]},{"0":[{"YEARAWARDED":1978,"OPPOSITETEAM":null},{"YEARAWARDED":1979,"OPPOSITETEAM":null},{"YEARAWARDED":1996,"OPPOSITETEAM":null},{"YEARAWARDED":2012,"OPPOSITETEAM":null}]},{"0":[{"YEARAWARDED":1979,"OPPOSITETEAM":null},{"YEARAWARDED":1994,"OPPOSITETEAM":null},{"YEARAWARDED":1996,"OPPOSITETEAM":null},{"YEARAWARDED":1997,"OPPOSITETEAM":null},{"YEARAWARDED":1998,"OPPOSITETEAM":null},{"YEARAWARDED":2005,"OPPOSITETEAM":null},{"YEARAWARDED":2011,"OPPOSITETEAM":null},{"YEARAWARDED":2012,"OPPOSITETEAM":null},{"YEARAWARDED":2013,"OPPOSITETEAM":null},{"YEARAWARDED":2014,"OPPOSITETEAM":null},{"YEARAWARDED":2016,"OPPOSITETEAM":null}]},{"0":[{"PLAYERID":78149,"PLAYER":"Jack Sikma","POSITION":"C","JERSEY":null,"SEASONSWITHTEAM":"1978-1986","YEAR":2019},{"PLAYERID":78500,"PLAYER":"Paul Westphal","POSITION":"G","JERSEY":null,"SEASONSWITHTEAM":"1981","YEAR":2019},{"PLAYERID":951,"PLAYER":"Ray Allen","POSITION":"G","JERSEY":null,"SEASONSWITHTEAM":"2002-2007","YEAR":2018},{"PLAYERID":76981,"PLAYER":"Spencer Haywood","POSITION":"F","JERSEY":null,"SEASONSWITHTEAM":"1971-1975","YEAR":2015},{"PLAYERID":36,"PLAYER":"Sarunas Marciulionis","POSITION":"G","JERSEY":null,"SEASONSWITHTEAM":"1995","YEAR":2014},{"PLAYERID":56,"PLAYER":"Gary Payton","POSITION":"G","JERSEY":null,"SEASONSWITHTEAM":"1991-2003","YEAR":2013},{"PLAYERID":77141,"PLAYER":"Dennis Johnson","POSITION":"G","JERSEY":null,"SEASONSWITHTEAM":"1977-1980","YEAR":2010},{"PLAYERID":121,"PLAYER":"Patrick Ewing","POSITION":"C","JERSEY":null,"SEASONSWITHTEAM":"2001","YEAR":2008},{"PLAYERID":78326,"PLAYER":"David Thompson","POSITION":"G","JERSEY":null,"SEASONSWITHTEAM":"1983-1984","YEAR":1996},{"PLAYERID":78530,"PLAYER":"Lenny Wilkens","POSITION":"G","JERSEY":null,"SEASONSWITHTEAM":"1969-1972","YEAR":1989}]},{"0":[{"PLAYERID":2555.0,"PLAYER":"Nick Collison","POSITION":"F-C","JERSEY":"4","SEASONSWITHTEAM":"2004-2018","YEAR":2019},{"PLAYERID":76981.0,"PLAYER":"Spencer Haywood","POSITION":"F","JERSEY":"24","SEASONSWITHTEAM":"1972-1975","YEAR":2007},{"PLAYERID":78549.0,"PLAYER":"Gus Williams","POSITION":"G","JERSEY":"1","SEASONSWITHTEAM":"1978-1984","YEAR":2004},{"PLAYERID":203.0,"PLAYER":"Nate McMillan","POSITION":"G","JERSEY":"10","SEASONSWITHTEAM":"1987-1998","YEAR":1999},{"PLAYERID":null,"PLAYER":"Bob Blackburn","POSITION":"Broadcaster","JERSEY":"","SEASONSWITHTEAM":"1968-1992","YEAR":1993},{"PLAYERID":78149.0,"PLAYER":"Jack Sikma","POSITION":"C","JERSEY":"43","SEASONSWITHTEAM":"1978-1986","YEAR":1992},{"PLAYERID":76272.0,"PLAYER":"Fred Brown","POSITION":"G","JERSEY":"32","SEASONSWITHTEAM":"1972-1984","YEAR":1986},{"PLAYERID":78530.0,"PLAYER":"Lenny Wilkens","POSITION":"G - Coach","JERSEY":"19","SEASONSWITHTEAM":"1969-1972, 1978-1985","YEAR":1979}]}]